drf_shop/__init__.py
drf_shop/admin.py
drf_shop/apps.py
drf_shop/migrations/0001_initial.py
drf_shop/migrations/__init__.py
drf_shop/models.py
drf_shop/py.typed
drf_shop/serializers.py
drf_shop/settings.py
drf_shop/urls.py
drf_shop/views.py
drf_shop-0.1.1.dist-info/WHEEL
drf_shop-0.1.1.dist-info/METADATA
drf_shop-0.1.1.dist-info/license_files/LICENSE
drf_shop-0.1.1.dist-info/RECORD
