Metadata-Version: 2.1
Name: drf-shop
Version: 0.1.1
Summary: Basic models, serializers, and view to quickly create a shop
Author-email: Xurvan <xurvan@tutanota.com>
Requires-Python: >=3.10
Requires-Dist: django>=4.1
Requires-Dist: djangorestframework>=3.13.1
